satellitevu/__init__.py
satellitevu/apis/__init__.py
satellitevu/apis/base.py
satellitevu/apis/base_test.py
satellitevu/apis/catalog.py
satellitevu/apis/catalog_test.py
satellitevu/apis/contracts.py
satellitevu/apis/exceptions.py
satellitevu/apis/helpers.py
satellitevu/apis/id.py
satellitevu/apis/id_test.py
satellitevu/apis/orders.py
satellitevu/apis/orders_test.py
satellitevu/apis/otm.py
satellitevu/apis/otm_test.py
satellitevu/auth/__init__.py
satellitevu/auth/auth.py
satellitevu/auth/auth_test.py
satellitevu/auth/cache.py
satellitevu/auth/cache_test.py
satellitevu/auth/exc.py
satellitevu/client.py
satellitevu/config.py
satellitevu/conftest.py
satellitevu/http/__init__.py
satellitevu/http/base.py
satellitevu/http/http_test.py
satellitevu/http/httpx.py
satellitevu/http/requests.py
satellitevu/http/urllib.py
satellitevu-6.0.0.dist-info/METADATA
satellitevu-6.0.0.dist-info/WHEEL
satellitevu-6.0.0.dist-info/licenses/LICENSE
satellitevu-6.0.0.dist-info/RECORD
