Metadata-Version: 2.4
Name: satellitevu
Version: 6.0.0
Summary: Client SDK for SatelliteVu's platform APIs
License: MIT
License-File: LICENSE
Author: Christian Wygoda
Author-email: christian.wygoda@satellitevu.com
Requires-Python: >=3.10,<4.0
Classifier: Development Status :: 7 - Inactive
Classifier: License :: OSI Approved :: MIT License
Classifier: Programming Language :: Python :: 3
Classifier: Programming Language :: Python :: 3.10
Classifier: Programming Language :: Python :: 3.11
Classifier: Programming Language :: Python :: 3.12
Classifier: Programming Language :: Python :: 3.13
Classifier: Programming Language :: Python :: 3.14
Requires-Dist: appdirs (>=1.4.4,<2.0.0)
